AUTHORS
LICENSE
MANIFEST.in
README.md
requirements.txt
setup.py
docs/man/man1/re-client.1
re_client.egg-info/PKG-INFO
re_client.egg-info/SOURCES.txt
re_client.egg-info/dependency_links.txt
re_client.egg-info/entry_points.txt
re_client.egg-info/top_level.txt
src/reclient/__init__.py
src/reclient/__init__.pyc
src/reclient/cli.py
src/reclient/colorize.py
src/reclient/colorize.pyc
src/reclient/connectors.py
src/reclient/connectors.pyc
src/reclient/utils.py
src/reclient/utils.pyc
test/test_connectors.py
test/test_init.py
test/test_utils.py