Metadata-Version: 1.0
Name: re-client
Version: 0.0.6-5
Summary: Release Engine Client Utilities
Home-page: https://github.com/rhinception/re-client
Author: See AUTHORS file
Author-email: inception@redhat.com
License: AGPLv3
Platform: UNKNOWN
